{
    "AD": {
        "collocated_vdir": "DOWN",
        "collocated_hdir": "RIGHT",
        "agent_egr": {
            "egr_buffer_size": [
                8,
                8
            ],
            "vpol_enable": true,
            "vpol_flip_enable": false
        },
        "tgr": {
            "egr_bounceable_buffer_size": 8,
            "egr_credited_buffer_size": 8,
            "igr_bounceable_buffer_size": 8,
            "igr_credited_buffer_size": [],
			"igr_sink_starvation_enable" : false
        }
    },
    "AK": {
        "collocated_vdir": "DOWN",
        "collocated_hdir": "RIGHT",
        "agent_egr": {
            "egr_buffer_size": [
                8,
                8
            ],
            "vpol_enable": true,
            "vpol_flip_enable": false
        },
        "tgr": {
            "egr_bounceable_buffer_size": 8,
            "egr_credited_buffer_size": 8,
            "igr_bounceable_buffer_size": 8,
            "igr_credited_buffer_size": [],
			"igr_sink_starvation_enable" : false
        }
    },
    "AKC": {
        "collocated_vdir": "DOWN",
        "collocated_hdir": "RIGHT",
        "agent_egr": {
            "egr_buffer_size": [
                8,
                8
            ],
            "vpol_enable": false,
            "vpol_flip_enable": false
        },
        "tgr": {
            "egr_bounceable_buffer_size": 8,
            "egr_credited_buffer_size": 8,
            "igr_bounceable_buffer_size": 8,
            "igr_credited_buffer_size": [],
			"igr_sink_starvation_enable" : false
        }
    },
    "BL": {
        "collocated_vdir": "DOWN",
        "collocated_hdir": "RIGHT",
        "agent_egr": {
            "egr_buffer_size": [
                16,
                16
            ],
            "vpol_enable": true,
            "vpol_flip_enable": false
        },
        "tgr": {
            "egr_bounceable_buffer_size": 8,
            "egr_credited_buffer_size": 8,
            "igr_bounceable_buffer_size": 8,
            "igr_credited_buffer_size": [],
			"igr_sink_starvation_enable" : false
        }
    },
    "IV": {
        "collocated_vdir": "DOWN",
        "collocated_hdir": "RIGHT",
        "agent_egr": {
            "egr_buffer_size": [
                8,
                8
            ],
            "vpol_enable": true,
            "vpol_flip_enable": false
        },
        "tgr": {
            "egr_bounceable_buffer_size": 8,
            "egr_credited_buffer_size": 8,
            "igr_bounceable_buffer_size": 8,
            "igr_credited_buffer_size": [],
			"igr_sink_starvation_enable" : false
        }
    }
}